<?xml version="1.0"?>
<annotation>
    <filename>000000000169.tif</filename>
    <source>
        <annotation>ESRI ArcGIS Pro</annotation>
    </source>
    <size>
        <width>256</width>
        <height>256</height>
        <depth>3</depth>
    </size>
    <object>
        <name>0</name>
        <bndbox>
            <xmin>28.67</xmin>
            <ymin>209.64</ymin>
            <xmax>40.67</xmax>
            <ymax>221.64</ymax>
        </bndbox>
    </object>
    <object>
        <name>0</name>
        <bndbox>
            <xmin>30.77</xmin>
            <ymin>166.17</ymin>
            <xmax>42.77</xmax>
            <ymax>178.17</ymax>
        </bndbox>
    </object>
    <object>
        <name>0</name>
        <bndbox>
            <xmin>31.97</xmin>
            <ymin>134.40</ymin>
            <xmax>43.97</xmax>
            <ymax>146.40</ymax>
        </bndbox>
    </object>
    <object>
        <name>0</name>
        <bndbox>
            <xmin>0.00</xmin>
            <ymin>67.84</ymin>
            <xmax>11.29</xmax>
            <ymax>79.84</ymax>
        </bndbox>
    </object>
    <object>
        <name>0</name>
        <bndbox>
            <xmin>121.90</xmin>
            <ymin>65.74</ymin>
            <xmax>133.90</xmax>
            <ymax>77.74</ymax>
        </bndbox>
    </object>
    <object>
        <name>0</name>
        <bndbox>
            <xmin>158.18</xmin>
            <ymin>69.04</ymin>
            <xmax>170.18</xmax>
            <ymax>81.04</ymax>
        </bndbox>
    </object>
    <object>
        <name>0</name>
        <bndbox>
            <xmin>182.76</xmin>
            <ymin>98.72</ymin>
            <xmax>194.76</xmax>
            <ymax>110.72</ymax>
        </bndbox>
    </object>
    <object>
        <name>0</name>
        <bndbox>
            <xmin>150.98</xmin>
            <ymin>39.66</ymin>
            <xmax>162.98</xmax>
            <ymax>51.66</ymax>
        </bndbox>
    </object>
</annotation>
